make_even_odd/LICENSE
make_even_odd/README.MD
make_even_odd/__init__.py
make_even_odd/requirements.txt
make_even_odd/thirdparty.json
make_even_odd-0.10.dist-info/LICENSE.rst
make_even_odd-0.10.dist-info/METADATA
make_even_odd-0.10.dist-info/WHEEL
make_even_odd-0.10.dist-info/top_level.txt
make_even_odd-0.10.dist-info/RECORD
